gap/pkg/float/COPYING
gap/pkg/float/PackageInfo.g
gap/pkg/float/README.md
gap/pkg/float/THANKS
gap/pkg/float/TODO
gap/pkg/float/config.h.in
gap/pkg/float/init.g
gap/pkg/float/libtool
gap/pkg/float/makedoc.g
gap/pkg/float/read.g
gap/pkg/float/bin/aarch64-unknown-linux-musl-default64-kv10/float.so
gap/pkg/float/build-aux/compile
gap/pkg/float/build-aux/config.guess~
gap/pkg/float/build-aux/config.sub~
gap/pkg/float/build-aux/depcomp
gap/pkg/float/build-aux/install-sh
gap/pkg/float/build-aux/install-sh~
gap/pkg/float/build-aux/ltmain.sh
gap/pkg/float/build-aux/missing
gap/pkg/float/lib/cxsc.gi
gap/pkg/float/lib/float.gd
gap/pkg/float/lib/fplll.gi
gap/pkg/float/lib/mpc.gi
gap/pkg/float/lib/mpfi.gi
gap/pkg/float/lib/mpfr.gi
gap/pkg/float/lib/pickle.g
gap/pkg/float/lib/polynomial.gi
gap/pkg/float/lib/pslq.gi
gap/pkg/float/tst/arithmetic.tst
gap/pkg/float/tst/fplll.tst
gap/pkg/float/tst/polynomials.tst
gap/pkg/float/tst/testall.g
passagemath_gap_pkg_float/__init__.py
passagemath_gap_pkg_float.libs/libfplll-56abb12b.so.9.0.0
passagemath_gap_pkg_float.libs/libgcc_s-2d945d6c.so.1
passagemath_gap_pkg_float.libs/libgmp-28992bcb.so.10.5.0
passagemath_gap_pkg_float.libs/libmpc-c436dce0.so.3.3.1
passagemath_gap_pkg_float.libs/libmpfi-fb53ce25.so.0.0.0
passagemath_gap_pkg_float.libs/libmpfr-1fc8ea36.so.6.2.2
passagemath_gap_pkg_float.libs/libstdc++-85f2cd6d.so.6.0.33
sage/all__sagemath_gap_pkg_float.py
sage/libs/all__sagemath_gap_pkg_float.py
sage/libs/gap_pkg_float.cpython-314t-aarch64-linux-musl.so
passagemath_gap_pkg_float-10.6.43.dist-info/METADATA
passagemath_gap_pkg_float-10.6.43.dist-info/METADATA.bak
passagemath_gap_pkg_float-10.6.43.dist-info/WHEEL
passagemath_gap_pkg_float-10.6.43.dist-info/top_level.txt
passagemath_gap_pkg_float-10.6.43.dist-info/RECORD
